MANIFEST.in
README.md
requirements.txt
setup.py
mocap/ArucoBot.py
mocap/ArucoDevice.py
mocap/ArucoHelper.py
mocap/__init__.py
mocap/_static_version.py
mocap/_version.py
mocap/calibration.yml
mocap/run_test.py
mocap/timestamp.py
mocap.egg-info/PKG-INFO
mocap.egg-info/SOURCES.txt
mocap.egg-info/dependency_links.txt
mocap.egg-info/requires.txt
mocap.egg-info/top_level.txt